airtag_detector/__init__.py
airtag_detector/detector.py
airtag_detector/homekit_controller.py
airtag_detector/homekit_setup.py
airtag_detector/setup.py
airtag_detector/test_bluetooth.py
airtag_detector/configs/config.py.template
airtag_detector/templates/airtag-detector.service
airtag_detector-1.0.1.data/data/share/airtag-detector/configs/config.py.template
airtag_detector-1.0.1.data/data/share/airtag-detector/systemd/airtag-detector.service
airtag_detector-1.0.1.dist-info/licenses/LICENSE
airtag_detector-1.0.1.dist-info/METADATA
airtag_detector-1.0.1.dist-info/WHEEL
airtag_detector-1.0.1.dist-info/entry_points.txt
airtag_detector-1.0.1.dist-info/top_level.txt
airtag_detector-1.0.1.dist-info/RECORD
