Metadata-Version: 2.4
Name: airtag-detector
Version: 1.0.1
Summary: Apple AirTag detector for Raspberry Pi with HomeKit integration
Home-page: https://github.com/nranderson/dogpi
Author: DogPi Project
Author-email: DogPi Project <contras-kite9t@icloud.com>
License-Expression: MIT
Project-URL: Homepage, https://github.com/nranderson/dogpi
Project-URL: Bug Reports, https://github.com/nranderson/dogpi/issues
Project-URL: Source, https://github.com/nranderson/dogpi
Project-URL: Documentation, https://github.com/nranderson/dogpi/blob/main/README.md
Keywords: airtag,bluetooth,raspberry-pi,homekit,home-automation,security,tracking-detection
Classifier: Development Status :: 4 - Beta
Classifier: Intended Audience :: End Users/Desktop
Classifier: Topic :: Home Automation
Classifier: Topic :: Security
Classifier: Topic :: System :: Hardware
Classifier: Programming Language :: Python :: 3
Classifier: Programming Language :: Python :: 3.8
Classifier: Programming Language :: Python :: 3.9
Classifier: Programming Language :: Python :: 3.10
Classifier: Programming Language :: Python :: 3.11
Classifier: Operating System :: POSIX :: Linux
Classifier: Environment :: No Input/Output (Daemon)
Requires-Python: >=3.8
License-File: LICENSE
Requires-Dist: bleak>=0.21.0
Requires-Dist: requests>=2.31.0
Provides-Extra: homekit
Requires-Dist: aiohomekit>=3.1.0; extra == "homekit"
Provides-Extra: dev
Requires-Dist: pytest>=7.0; extra == "dev"
Requires-Dist: black; extra == "dev"
Requires-Dist: flake8; extra == "dev"
Requires-Dist: mypy; extra == "dev"
Dynamic: author
Dynamic: home-page
Dynamic: license-file
Dynamic: requires-python
